{
  "pitcher_id": "668971",
  "pitcher_name": "Mason Hickman",
  "mlbam_id": "668971",
  "arm_angle_source": "dataset",
  "pitches": [
    {
      "code": "FF",
      "title": "four-seam fastball",
      "color": "#D22D49",
      "count": 149,
      "pitch_percent": 0.3547619047619048,
      "rhh_percent": 0.3274021352313167,
      "lhh_percent": 0.41007194244604317,
      "start_speed": 90.76979865771807,
      "max_start_speed": 92.8,
      "ivb": 15.728187919463082,
      "hb": 9.524161073825505,
      "release_pos_z": 6.055682349712112,
      "release_pos_x": 1.7675695557855668,
      "extension": 7.120299213978869,
      "active_spin_percent": null
    },
    {
      "code": "CU",
      "title": "curveball",
      "color": "#00D2ED",
      "count": 112,
      "pitch_percent": 0.26666666666666666,
      "rhh_percent": 0.26334519572953735,
      "lhh_percent": 0.2733812949640288,
      "start_speed": 74.07142857142857,
      "max_start_speed": 76.2,
      "ivb": -6.850892857142857,
      "hb": -12.274107142857144,
      "release_pos_z": 6.073782293533147,
      "release_pos_x": 1.8599989590320558,
      "extension": 6.970773913354291,
      "active_spin_percent": null
    },
    {
      "code": "SL",
      "title": "slider",
      "color": "#EEE716",
      "count": 72,
      "pitch_percent": 0.17142857142857143,
      "rhh_percent": 0.2206405693950178,
      "lhh_percent": 0.07194244604316546,
      "start_speed": 83.12638888888891,
      "max_start_speed": 85.8,
      "ivb": 3.223611111111111,
      "hb": -2.569444444444444,
      "release_pos_z": 6.040099003361299,
      "release_pos_x": 1.9716305782641963,
      "extension": 6.98298635753596,
      "active_spin_percent": null
    },
    {
      "code": "SI",
      "title": "sinker",
      "color": "#FE9E00",
      "count": 56,
      "pitch_percent": 0.13333333333333333,
      "rhh_percent": 0.16725978647686832,
      "lhh_percent": 0.06474820143884892,
      "start_speed": 90.44107142857146,
      "max_start_speed": 93,
      "ivb": 10.599999999999998,
      "hb": 15.135714285714286,
      "release_pos_z": 6.0624331071548045,
      "release_pos_x": 1.7275716886659072,
      "extension": 7.10023307543967,
      "active_spin_percent": null
    },
    {
      "code": "CH",
      "title": "changeup",
      "color": "#1DBF3A",
      "count": 31,
      "pitch_percent": 0.07380952380952381,
      "rhh_percent": 0.021352313167259787,
      "lhh_percent": 0.17985611510791366,
      "start_speed": 83.60645161290321,
      "max_start_speed": 86.5,
      "ivb": 4.145161290322581,
      "hb": 9.23225806451613,
      "release_pos_z": 6.068832858323298,
      "release_pos_x": 1.7727682694415081,
      "extension": 7.110381003961416,
      "active_spin_percent": null
    }
  ]
}