{
  "pitcher_id": "673540",
  "pitcher_name": "Kodai Senga",
  "mlbam_id": "673540",
  "arm_angle_source": "dataset",
  "pitches": [
    {
      "code": "FF",
      "title": "four-seam fastball",
      "color": "#D22D49",
      "count": 53,
      "pitch_percent": 0.3419354838709677,
      "rhh_percent": 0.36,
      "lhh_percent": 0.3090909090909091,
      "start_speed": 93.4679245283019,
      "max_start_speed": 95.4,
      "ivb": 16.5811320754717,
      "hb": 7.209433962264149,
      "release_pos_z": 6.246131242295715,
      "release_pos_x": 2.1365818936479894,
      "extension": 6.13535664687087,
      "active_spin_percent": null
    },
    {
      "code": "FO",
      "title": "forkball",
      "color": "#55CCAB",
      "count": 39,
      "pitch_percent": 0.25161290322580643,
      "rhh_percent": 0.23,
      "lhh_percent": 0.2909090909090909,
      "start_speed": 80.60512820512821,
      "max_start_speed": 82.8,
      "ivb": 0.5846153846153848,
      "hb": 9.38205128205128,
      "release_pos_z": 6.303521689131235,
      "release_pos_x": 2.1720112163120167,
      "extension": 5.91451466235964,
      "active_spin_percent": null
    },
    {
      "code": "FC",
      "title": "cutter",
      "color": "#933F2C",
      "count": 39,
      "pitch_percent": 0.25161290322580643,
      "rhh_percent": 0.26,
      "lhh_percent": 0.23636363636363636,
      "start_speed": 87.68205128205126,
      "max_start_speed": 91.7,
      "ivb": 7.717948717948718,
      "hb": -0.2717948717948719,
      "release_pos_z": 6.3225545938926855,
      "release_pos_x": 2.000817553527922,
      "extension": 6.084355115441102,
      "active_spin_percent": null
    },
    {
      "code": "ST",
      "title": "sweeper",
      "color": "#DDB43A",
      "count": 14,
      "pitch_percent": 0.09032258064516129,
      "rhh_percent": 0.07,
      "lhh_percent": 0.12727272727272726,
      "start_speed": 78.21428571428571,
      "max_start_speed": 82.1,
      "ivb": -3.235714285714286,
      "hb": -9.335714285714287,
      "release_pos_z": 6.249337562894619,
      "release_pos_x": 2.041057488594923,
      "extension": 5.948325460926666,
      "active_spin_percent": null
    },
    {
      "code": "SI",
      "title": "sinker",
      "color": "#FE9E00",
      "count": 6,
      "pitch_percent": 0.03870967741935484,
      "rhh_percent": 0.05,
      "lhh_percent": 0.01818181818181818,
      "start_speed": 86.33333333333333,
      "max_start_speed": 87.8,
      "ivb": 7.633333333333333,
      "hb": 15.449999999999998,
      "release_pos_z": 6.259289540743321,
      "release_pos_x": 2.270993945143515,
      "extension": 5.8612042998622185,
      "active_spin_percent": null
    },
    {
      "code": "CU",
      "title": "curveball",
      "color": "#00D2ED",
      "count": 4,
      "pitch_percent": 0.025806451612903226,
      "rhh_percent": 0.03,
      "lhh_percent": 0.01818181818181818,
      "start_speed": 68.19999999999999,
      "max_start_speed": 71.6,
      "ivb": -12.100000000000001,
      "hb": -8.4,
      "release_pos_z": 6.258199435367018,
      "release_pos_x": 1.8284687664879702,
      "extension": 5.945779379878457,
      "active_spin_percent": null
    }
  ]
}