{
  "pitcher_id": "675375",
  "pitcher_name": "Cory Lewis",
  "mlbam_id": "675375",
  "arm_angle_source": "dataset",
  "pitches": [
    {
      "code": "FF",
      "title": "four-seam fastball",
      "color": "#D22D49",
      "count": 438,
      "pitch_percent": 0.28423101881894874,
      "rhh_percent": 0.28040540540540543,
      "lhh_percent": 0.2894333843797856,
      "start_speed": 89.97853881278544,
      "max_start_speed": 92.8,
      "ivb": 18.731278538812788,
      "hb": 6.3755707762557075,
      "release_pos_z": 6.578725748852712,
      "release_pos_x": 0.30399019628622215,
      "extension": 6.339391480594454,
      "active_spin_percent": null
    },
    {
      "code": "SL",
      "title": "slider",
      "color": "#EEE716",
      "count": 253,
      "pitch_percent": 0.16417910447761194,
      "rhh_percent": 0.2545045045045045,
      "lhh_percent": 0.04134762633996937,
      "start_speed": 80.76600790513828,
      "max_start_speed": 85.3,
      "ivb": 0.12332015810276688,
      "hb": 0.39011857707509867,
      "release_pos_z": 6.439757250917846,
      "release_pos_x": 0.48647621106235805,
      "extension": 6.1925988955133935,
      "active_spin_percent": null
    },
    {
      "code": "CU",
      "title": "curveball",
      "color": "#00D2ED",
      "count": 171,
      "pitch_percent": 0.11096690460739779,
      "rhh_percent": 0.06531531531531531,
      "lhh_percent": 0.17304747320061256,
      "start_speed": 79.55146198830413,
      "max_start_speed": 82.8,
      "ivb": -12.220467836257312,
      "hb": -1.3374269005847954,
      "release_pos_z": 6.499586641011778,
      "release_pos_x": 0.41302503573489274,
      "extension": 6.181501903609663,
      "active_spin_percent": null
    },
    {
      "code": "FC",
      "title": "cutter",
      "color": "#933F2C",
      "count": 102,
      "pitch_percent": 0.06619078520441272,
      "rhh_percent": 0.061936936936936936,
      "lhh_percent": 0.07197549770290965,
      "start_speed": 86.40882352941175,
      "max_start_speed": 90.2,
      "ivb": 10.24509803921569,
      "hb": -2.7431372549019604,
      "release_pos_z": 6.45421211932637,
      "release_pos_x": 0.6094485602635559,
      "extension": 6.316173012556204,
      "active_spin_percent": null
    },
    {
      "code": "CH",
      "title": "changeup",
      "color": "#1DBF3A",
      "count": 55,
      "pitch_percent": 0.035691109669046074,
      "rhh_percent": 0.01126126126126126,
      "lhh_percent": 0.06891271056661562,
      "start_speed": 81.81636363636363,
      "max_start_speed": 85.8,
      "ivb": 10.932727272727272,
      "hb": 11.243636363636364,
      "release_pos_z": 6.483209903699471,
      "release_pos_x": 0.5272710047887299,
      "extension": 6.192363847389407,
      "active_spin_percent": null
    }
  ]
}