{
  "pitcher_id": "686642",
  "pitcher_name": "Fraser Ellard",
  "mlbam_id": "686642",
  "arm_angle_source": "dataset",
  "pitches": [
    {
      "code": "FF",
      "title": "four-seam fastball",
      "color": "#D22D49",
      "count": 225,
      "pitch_percent": 0.4849137931034483,
      "rhh_percent": 0.5991902834008097,
      "lhh_percent": 0.3548387096774194,
      "start_speed": 94.60622222222219,
      "max_start_speed": 97.3,
      "ivb": 14.07999999999999,
      "hb": 9.857333333333337,
      "release_pos_z": 5.72125044219584,
      "release_pos_x": 2.756031304862728,
      "extension": 6.114895068911479,
      "active_spin_percent": null
    },
    {
      "code": "SL",
      "title": "slider",
      "color": "#EEE716",
      "count": 124,
      "pitch_percent": 0.2672413793103448,
      "rhh_percent": 0.1902834008097166,
      "lhh_percent": 0.3548387096774194,
      "start_speed": 84.77741935483874,
      "max_start_speed": 87.6,
      "ivb": -2.144354838709678,
      "hb": -8.137903225806452,
      "release_pos_z": 5.700127776496979,
      "release_pos_x": 2.854347497318773,
      "extension": 6.020737155032021,
      "active_spin_percent": null
    },
    {
      "code": "CH",
      "title": "changeup",
      "color": "#1DBF3A",
      "count": 52,
      "pitch_percent": 0.11206896551724138,
      "rhh_percent": 0.15384615384615385,
      "lhh_percent": 0.06451612903225806,
      "start_speed": 90.50961538461539,
      "max_start_speed": 93.3,
      "ivb": 3.761538461538462,
      "hb": 11.05,
      "release_pos_z": 5.743342052278541,
      "release_pos_x": 2.812241913802203,
      "extension": 6.095969440447377,
      "active_spin_percent": null
    },
    {
      "code": "SI",
      "title": "sinker",
      "color": "#FE9E00",
      "count": 43,
      "pitch_percent": 0.09267241379310345,
      "rhh_percent": 0.004048582995951417,
      "lhh_percent": 0.1935483870967742,
      "start_speed": 93.31162790697675,
      "max_start_speed": 95.7,
      "ivb": 4.5372093023255795,
      "hb": 14.06279069767442,
      "release_pos_z": 5.760620746511784,
      "release_pos_x": 2.8289745765049896,
      "extension": 6.041384403814528,
      "active_spin_percent": null
    },
    {
      "code": "FC",
      "title": "cutter",
      "color": "#933F2C",
      "count": 19,
      "pitch_percent": 0.040948275862068964,
      "rhh_percent": 0.05263157894736842,
      "lhh_percent": 0.027649769585253458,
      "start_speed": 90.72105263157896,
      "max_start_speed": 92.7,
      "ivb": 5.436842105263158,
      "hb": -0.7157894736842105,
      "release_pos_z": 5.780735969005801,
      "release_pos_x": 2.870755146831922,
      "extension": 6.086100180946147,
      "active_spin_percent": null
    }
  ]
}