{
  "pitcher_id": "687273",
  "pitcher_name": "Quinn Mathews",
  "mlbam_id": "687273",
  "arm_angle_source": "dataset",
  "pitches": [
    {
      "code": "FF",
      "title": "four-seam fastball",
      "color": "#D22D49",
      "count": 696,
      "pitch_percent": 0.40324449594438005,
      "rhh_percent": 0.40807914262159933,
      "lhh_percent": 0.391812865497076,
      "start_speed": 93.08117816091959,
      "max_start_speed": 96,
      "ivb": 16.02097701149424,
      "hb": 5.4586206896551746,
      "release_pos_z": 5.644295397240584,
      "release_pos_x": 1.5947245771739595,
      "extension": 6.43967966531042,
      "active_spin_percent": null
    },
    {
      "code": "SL",
      "title": "slider",
      "color": "#EEE716",
      "count": 411,
      "pitch_percent": 0.2381228273464658,
      "rhh_percent": 0.2019785655399835,
      "lhh_percent": 0.3235867446393762,
      "start_speed": 85.06350364963508,
      "max_start_speed": 90,
      "ivb": 3.3333333333333344,
      "hb": -4.370559610705592,
      "release_pos_z": 5.645610619867839,
      "release_pos_x": 1.5693290083194897,
      "extension": 6.374698831867993,
      "active_spin_percent": null
    },
    {
      "code": "CH",
      "title": "changeup",
      "color": "#1DBF3A",
      "count": 368,
      "pitch_percent": 0.21320973348783315,
      "rhh_percent": 0.28606760098928274,
      "lhh_percent": 0.04093567251461988,
      "start_speed": 81.60190217391312,
      "max_start_speed": 87.5,
      "ivb": 4.876358695652171,
      "hb": 12.657608695652172,
      "release_pos_z": 5.487615811323704,
      "release_pos_x": 1.8059807753160981,
      "extension": 6.23411024895114,
      "active_spin_percent": null
    },
    {
      "code": "CU",
      "title": "curveball",
      "color": "#00D2ED",
      "count": 163,
      "pitch_percent": 0.09443800695249131,
      "rhh_percent": 0.10222588623248145,
      "lhh_percent": 0.07602339181286549,
      "start_speed": 75.99325153374232,
      "max_start_speed": 79.2,
      "ivb": -10.699386503067483,
      "hb": -9.60368098159509,
      "release_pos_z": 5.873910114896356,
      "release_pos_x": 1.245025773724756,
      "extension": 6.249554607286742,
      "active_spin_percent": null
    },
    {
      "code": "SI",
      "title": "sinker",
      "color": "#FE9E00",
      "count": 88,
      "pitch_percent": 0.05098493626882966,
      "rhh_percent": 0.0016488046166529267,
      "lhh_percent": 0.16764132553606237,
      "start_speed": 92.67272727272727,
      "max_start_speed": 95.6,
      "ivb": 12.579545454545455,
      "hb": 13.1625,
      "release_pos_z": 5.630015455120535,
      "release_pos_x": 1.6249955572417862,
      "extension": 6.414869899813919,
      "active_spin_percent": null
    }
  ]
}