{
  "pitcher_id": "688214",
  "pitcher_name": "Ryan Jennings",
  "mlbam_id": "688214",
  "arm_angle_source": "dataset",
  "pitches": [
    {
      "code": "SI",
      "title": "sinker",
      "color": "#FE9E00",
      "count": 377,
      "pitch_percent": 0.4889753566796368,
      "rhh_percent": 0.47058823529411764,
      "lhh_percent": 0.5160256410256411,
      "start_speed": 94.7933687002653,
      "max_start_speed": 97.1,
      "ivb": 14.276657824933693,
      "hb": 13.89257294429709,
      "release_pos_z": 5.657391130596692,
      "release_pos_x": 2.445516389100326,
      "extension": 6.1220621606661085,
      "active_spin_percent": null
    },
    {
      "code": "SL",
      "title": "slider",
      "color": "#EEE716",
      "count": 223,
      "pitch_percent": 0.2892347600518807,
      "rhh_percent": 0.3485838779956427,
      "lhh_percent": 0.20192307692307693,
      "start_speed": 86.6762331838565,
      "max_start_speed": 88.6,
      "ivb": 5.073094170403589,
      "hb": 2.3766816143497738,
      "release_pos_z": 5.67311915308128,
      "release_pos_x": 2.453576211022532,
      "extension": 6.008102652037652,
      "active_spin_percent": null
    },
    {
      "code": "CU",
      "title": "curveball",
      "color": "#00D2ED",
      "count": 116,
      "pitch_percent": 0.1504539559014267,
      "rhh_percent": 0.1328976034858388,
      "lhh_percent": 0.1762820512820513,
      "start_speed": 82.41810344827587,
      "max_start_speed": 85.7,
      "ivb": -6.7698275862068975,
      "hb": 0.588793103448276,
      "release_pos_z": 5.733637729471692,
      "release_pos_x": 2.3683517018571334,
      "extension": 6.045654129990404,
      "active_spin_percent": null
    },
    {
      "code": "CH",
      "title": "changeup",
      "color": "#1DBF3A",
      "count": 55,
      "pitch_percent": 0.07133592736705577,
      "rhh_percent": 0.04793028322440087,
      "lhh_percent": 0.10576923076923077,
      "start_speed": 86.55636363636363,
      "max_start_speed": 89.1,
      "ivb": 3.161818181818182,
      "hb": 12.825454545454544,
      "release_pos_z": 5.664679198074625,
      "release_pos_x": 2.4110797612044648,
      "extension": 6.146974046925082,
      "active_spin_percent": null
    }
  ]
}