{
  "pitcher_id": "804619",
  "pitcher_name": "John Klein",
  "mlbam_id": "804619",
  "arm_angle_source": "dataset",
  "pitches": [
    {
      "code": "FF",
      "title": "four-seam fastball",
      "color": "#D22D49",
      "count": 152,
      "pitch_percent": 0.2980392156862745,
      "rhh_percent": 0.2946058091286307,
      "lhh_percent": 0.30111524163568776,
      "start_speed": 94.52631578947371,
      "max_start_speed": 97.1,
      "ivb": 16.378289473684216,
      "hb": 10.295394736842104,
      "release_pos_z": 6.164378111852802,
      "release_pos_x": 1.1350393663783533,
      "extension": 6.6603485569521395,
      "active_spin_percent": null
    },
    {
      "code": "FC",
      "title": "cutter",
      "color": "#933F2C",
      "count": 119,
      "pitch_percent": 0.23333333333333334,
      "rhh_percent": 0.2863070539419087,
      "lhh_percent": 0.18587360594795538,
      "start_speed": 89.02941176470593,
      "max_start_speed": 91.5,
      "ivb": 8.19579831932773,
      "hb": -1.9336134453781517,
      "release_pos_z": 6.008063797086904,
      "release_pos_x": 1.3236370049047526,
      "extension": 6.640993660824461,
      "active_spin_percent": null
    },
    {
      "code": "SI",
      "title": "sinker",
      "color": "#FE9E00",
      "count": 101,
      "pitch_percent": 0.1980392156862745,
      "rhh_percent": 0.18672199170124482,
      "lhh_percent": 0.20817843866171004,
      "start_speed": 94.73762376237623,
      "max_start_speed": 97.4,
      "ivb": 14.97524752475248,
      "hb": 13.195049504950498,
      "release_pos_z": 6.157702717962336,
      "release_pos_x": 1.1413372437149307,
      "extension": 6.706194336799326,
      "active_spin_percent": null
    },
    {
      "code": "CU",
      "title": "curveball",
      "color": "#00D2ED",
      "count": 79,
      "pitch_percent": 0.15490196078431373,
      "rhh_percent": 0.17842323651452283,
      "lhh_percent": 0.13382899628252787,
      "start_speed": 80.27721518987343,
      "max_start_speed": 83.4,
      "ivb": -12.253164556962023,
      "hb": -12.632911392405063,
      "release_pos_z": 6.023340316489857,
      "release_pos_x": 1.292660252724311,
      "extension": 6.569657868836766,
      "active_spin_percent": null
    },
    {
      "code": "CH",
      "title": "changeup",
      "color": "#1DBF3A",
      "count": 59,
      "pitch_percent": 0.11568627450980393,
      "rhh_percent": 0.05394190871369295,
      "lhh_percent": 0.17100371747211895,
      "start_speed": 86.23389830508475,
      "max_start_speed": 88.6,
      "ivb": 2.6949152542372876,
      "hb": 13.171186440677964,
      "release_pos_z": 5.8810165629100135,
      "release_pos_x": 1.344465711802809,
      "extension": 6.64122279426792,
      "active_spin_percent": null
    }
  ]
}