{
  "pitcher_id": "687259",
  "pitcher_name": "Luke Bell",
  "mlbam_id": "687259",
  "arm_angle_source": "dataset",
  "pitches": [
    {
      "code": "FF",
      "title": "four-seam fastball",
      "color": "#D22D49",
      "count": 3,
      "pitch_percent": 0.42857142857142855,
      "rhh_percent": 0.6,
      "lhh_percent": 0,
      "start_speed": 90.33333333333333,
      "max_start_speed": 92,
      "ivb": 15.233333333333334,
      "hb": 0.6999999999999998,
      "release_pos_z": 5.920476455003662,
      "release_pos_x": 1.3146687857730053,
      "extension": 6.516163742770709,
      "pitches": 3,
      "whiffs": 0,
      "swings": 2,
      "spin_rate": 2065,
      "swing_miss_percent": 0,
      "arm_angle": null,
      "barrels_per_pa_percent": 0,
      "hardhit_percent": 0,
      "whiffs_per_pitch": 0,
      "active_spin_percent": null
    },
    {
      "code": "FC",
      "title": "cutter",
      "color": "#933F2C",
      "count": 3,
      "pitch_percent": 0.42857142857142855,
      "rhh_percent": 0.2,
      "lhh_percent": 1,
      "start_speed": 85,
      "max_start_speed": 85.5,
      "ivb": 2.3333333333333335,
      "hb": -2.1999999999999997,
      "release_pos_z": 5.72760278747175,
      "release_pos_x": 1.7081105187567427,
      "extension": 6.583641903371048,
      "pitches": 2,
      "whiffs": 0,
      "swings": 1,
      "spin_rate": 2224,
      "swing_miss_percent": 0,
      "arm_angle": null,
      "barrels_per_pa_percent": null,
      "hardhit_percent": null,
      "whiffs_per_pitch": 0,
      "active_spin_percent": null
    },
    {
      "code": "CU",
      "title": "curveball",
      "color": "#00D2ED",
      "count": 1,
      "pitch_percent": 0.14285714285714285,
      "rhh_percent": 0.2,
      "lhh_percent": 0,
      "start_speed": 80.5,
      "max_start_speed": 80.5,
      "ivb": -4.3,
      "hb": -13,
      "release_pos_z": 5.699194727711023,
      "release_pos_x": 1.7233052988885948,
      "extension": 6.392240412274392,
      "pitches": 1,
      "whiffs": 0,
      "swings": 1,
      "spin_rate": 2495,
      "swing_miss_percent": 0,
      "arm_angle": null,
      "barrels_per_pa_percent": 0,
      "hardhit_percent": 0,
      "whiffs_per_pitch": 0,
      "active_spin_percent": null
    }
  ]
}