{
  "pitcher_id": "666659",
  "pitcher_name": "Sauryn Lao",
  "pitches": [
    {
      "code": "SL",
      "title": "slider",
      "color": "#EEE716",
      "count": 89,
      "pitch_percent": 0.4810810810810811,
      "rhh_percent": 0.6,
      "lhh_percent": 0.325,
      "start_speed": 86.85168539325839,
      "max_start_speed": 88.9,
      "ivb": 6.86292134831461,
      "hb": -2.5988764044943826,
      "release_pos_z": 5.69127873599483,
      "release_pos_x": 1.1804856377076436,
      "extension": 6.237919362046342,
      "pitches": 88,
      "whiffs": 18,
      "swings": 45,
      "spin_rate": 2247,
      "swing_miss_percent": 40,
      "arm_angle": 31.6,
      "barrels_per_pa_percent": 4.545454545454546,
      "hardhit_percent": 42.857142857142854,
      "whiffs_per_pitch": 0.20454545454545456,
      "active_spin_percent": 34.6
    },
    {
      "code": "FF",
      "title": "four-seam fastball",
      "color": "#D22D49",
      "count": 55,
      "pitch_percent": 0.2972972972972973,
      "rhh_percent": 0.22857142857142856,
      "lhh_percent": 0.3875,
      "start_speed": 92.78181818181815,
      "max_start_speed": 95.8,
      "ivb": 11.889090909090905,
      "hb": 6.096363636363637,
      "release_pos_z": 5.961439731513432,
      "release_pos_x": 0.962067284133225,
      "extension": 6.250476380147794,
      "pitches": 55,
      "whiffs": 7,
      "swings": 29,
      "spin_rate": 2233,
      "swing_miss_percent": 24.1,
      "arm_angle": 37.7,
      "barrels_per_pa_percent": 25,
      "hardhit_percent": 50,
      "whiffs_per_pitch": 0.12727272727272726,
      "active_spin_percent": 77.5
    },
    {
      "code": "SI",
      "title": "sinker",
      "color": "#FE9E00",
      "count": 27,
      "pitch_percent": 0.14594594594594595,
      "rhh_percent": 0.14285714285714285,
      "lhh_percent": 0.15,
      "start_speed": 93.12962962962962,
      "max_start_speed": 94.9,
      "ivb": 6.425925925925926,
      "hb": 14.529629629629628,
      "release_pos_z": 5.8511434564755875,
      "release_pos_x": 0.9686856081297033,
      "extension": 6.328486479686824,
      "pitches": 27,
      "whiffs": 3,
      "swings": 18,
      "spin_rate": 2199,
      "swing_miss_percent": 16.7,
      "arm_angle": 34.8,
      "barrels_per_pa_percent": 0,
      "hardhit_percent": 77.77777777777779,
      "whiffs_per_pitch": 0.1111111111111111,
      "active_spin_percent": 79.1
    },
    {
      "code": "CH",
      "title": "changeup",
      "color": "#1DBF3A",
      "count": 14,
      "pitch_percent": 0.07567567567567568,
      "rhh_percent": 0.02857142857142857,
      "lhh_percent": 0.1375,
      "start_speed": 86.97142857142855,
      "max_start_speed": 88.5,
      "ivb": 6.835714285714287,
      "hb": 14.764285714285714,
      "release_pos_z": 5.835583982224855,
      "release_pos_x": 0.9317741345847564,
      "extension": 6.47417117091898,
      "pitches": 14,
      "whiffs": 1,
      "swings": 4,
      "spin_rate": 1885,
      "swing_miss_percent": 25,
      "arm_angle": 34.9,
      "barrels_per_pa_percent": 0,
      "hardhit_percent": 33.33333333333333,
      "whiffs_per_pitch": 0.07142857142857142,
      "active_spin_percent": 82.2
    }
  ]
}