{
  "pitcher_id": "669459",
  "pitcher_name": "Kyle Nelson",
  "pitches": [
    {
      "code": "SL",
      "title": "slider",
      "color": "#EEE716",
      "count": 24,
      "pitch_percent": 0.5454545454545454,
      "rhh_percent": 0.5333333333333333,
      "lhh_percent": 0.5714285714285714,
      "start_speed": 84.24166666666666,
      "max_start_speed": 85.8,
      "ivb": 2.8625000000000003,
      "hb": -1.9708333333333334,
      "release_pos_z": 5.819467228950902,
      "release_pos_x": 1.0425823426024128,
      "extension": 6.076570870330033,
      "pitches": 24,
      "whiffs": 4,
      "swings": 10,
      "spin_rate": 2793,
      "swing_miss_percent": 40,
      "arm_angle": 44.9,
      "barrels_per_pa_percent": 25,
      "hardhit_percent": 50,
      "whiffs_per_pitch": 0.16666666666666666,
      "active_spin_percent": null
    },
    {
      "code": "FF",
      "title": "four-seam fastball",
      "color": "#D22D49",
      "count": 19,
      "pitch_percent": 0.4318181818181818,
      "rhh_percent": 0.43333333333333335,
      "lhh_percent": 0.42857142857142855,
      "start_speed": 89.93684210526317,
      "max_start_speed": 90.8,
      "ivb": 16.842105263157894,
      "hb": 7.2789473684210515,
      "release_pos_z": 5.705459958964997,
      "release_pos_x": 1.0064895308847963,
      "extension": 6.208789753581459,
      "pitches": 19,
      "whiffs": 0,
      "swings": 5,
      "spin_rate": 2183,
      "swing_miss_percent": 0,
      "arm_angle": 42.3,
      "barrels_per_pa_percent": 0,
      "hardhit_percent": 0,
      "whiffs_per_pitch": 0,
      "active_spin_percent": null
    },
    {
      "code": "FC",
      "title": "cutter",
      "color": "#933F2C",
      "count": 1,
      "pitch_percent": 0.022727272727272728,
      "rhh_percent": 0.03333333333333333,
      "lhh_percent": 0,
      "start_speed": 88.5,
      "max_start_speed": 88.5,
      "ivb": 14.5,
      "hb": 7.6,
      "release_pos_z": 5.681220628526062,
      "release_pos_x": 1.0058221416893558,
      "extension": 6.066188587576766,
      "pitches": 1,
      "whiffs": 0,
      "swings": 0,
      "spin_rate": 2027,
      "swing_miss_percent": null,
      "arm_angle": 44.5,
      "barrels_per_pa_percent": null,
      "hardhit_percent": null,
      "whiffs_per_pitch": 0,
      "active_spin_percent": null
    }
  ]
}