{
  "pitcher_id": "688297",
  "pitcher_name": "Chris Roycroft",
  "pitches": [
    {
      "code": "SI",
      "title": "sinker",
      "color": "#FE9E00",
      "count": 190,
      "pitch_percent": 0.48223350253807107,
      "rhh_percent": 0.6032388663967612,
      "lhh_percent": 0.2789115646258503,
      "start_speed": 95.3568421052632,
      "max_start_speed": 98.2,
      "ivb": 3.691052631578947,
      "hb": 16.66157894736841,
      "release_pos_z": 4.861457414810274,
      "release_pos_x": 1.8536366806865963,
      "extension": 6.97716069617881,
      "pitches": 189,
      "whiffs": 16,
      "swings": 82,
      "spin_rate": 2134,
      "swing_miss_percent": 19.5,
      "arm_angle": 15.4,
      "barrels_per_pa_percent": 10,
      "hardhit_percent": 54.054054054054056,
      "whiffs_per_pitch": 0.08465608465608465,
      "active_spin_percent": 93.1
    },
    {
      "code": "FF",
      "title": "four-seam fastball",
      "color": "#D22D49",
      "count": 112,
      "pitch_percent": 0.28426395939086296,
      "rhh_percent": 0.12955465587044535,
      "lhh_percent": 0.54421768707483,
      "start_speed": 95.6517857142857,
      "max_start_speed": 98.7,
      "ivb": 9.011607142857143,
      "hb": 7.0982142857142865,
      "release_pos_z": 5.061203591969312,
      "release_pos_x": 1.8151676869998037,
      "extension": 6.88222565806855,
      "pitches": 111,
      "whiffs": 18,
      "swings": 68,
      "spin_rate": 2197,
      "swing_miss_percent": 26.5,
      "arm_angle": 18.8,
      "barrels_per_pa_percent": 3.7037037037037033,
      "hardhit_percent": 40,
      "whiffs_per_pitch": 0.16216216216216217,
      "active_spin_percent": 68.2
    },
    {
      "code": "FC",
      "title": "cutter",
      "color": "#933F2C",
      "count": 92,
      "pitch_percent": 0.233502538071066,
      "rhh_percent": 0.26720647773279355,
      "lhh_percent": 0.17687074829931973,
      "start_speed": 88.36195652173915,
      "max_start_speed": 92.3,
      "ivb": 0.5836956521739131,
      "hb": -4.748913043478261,
      "release_pos_z": 4.9405034106340056,
      "release_pos_x": 1.9524716363569878,
      "extension": 7.00555226116212,
      "pitches": 92,
      "whiffs": 6,
      "swings": 35,
      "spin_rate": 2322,
      "swing_miss_percent": 17.1,
      "arm_angle": 18.1,
      "barrels_per_pa_percent": 9.523809523809524,
      "hardhit_percent": 42.857142857142854,
      "whiffs_per_pitch": 0.06521739130434782,
      "active_spin_percent": 31.5
    }
  ]
}